{
    "NextToken": "",
    "SpotPriceHistory": [
        {
            "AvailabilityZone": "us-east-1e",
            "InstanceType": "p2.8xlarge",
            "ProductDescription": "Linux/UNIX",
            "SpotPrice": "2.196000",
            "Timestamp": "2020-03-05T08:19:45.000Z"
        },
        {
            "AvailabilityZone": "us-east-1b",
            "InstanceType": "p2.8xlarge",
            "ProductDescription": "Linux/UNIX",
            "SpotPrice": "2.160000",
            "Timestamp": "2020-03-05T06:09:06.000Z"
        },
        {
            "AvailabilityZone": "us-east-1f",
            "InstanceType": "p2.8xlarge",
            "ProductDescription": "Linux/UNIX",
            "SpotPrice": "7.200000",
            "Timestamp": "2020-03-05T06:09:06.000Z"
        },
        {
            "AvailabilityZone": "us-east-1a",
            "InstanceType": "p2.8xlarge",
            "ProductDescription": "Linux/UNIX",
            "SpotPrice": "2.160000",
            "Timestamp": "2020-03-05T06:09:06.000Z"
        },
        {
            "AvailabilityZone": "us-east-1e",
            "InstanceType": "p2.8xlarge",
            "ProductDescription": "Linux/UNIX",
            "SpotPrice": "2.184900",
            "Timestamp": "2020-03-05T06:09:06.000Z"
        },
        {
            "AvailabilityZone": "us-east-1d",
            "InstanceType": "p2.8xlarge",
            "ProductDescription": "Linux/UNIX",
            "SpotPrice": "2.160000",
            "Timestamp": "2020-03-05T06:09:06.000Z"
        },
        {
            "AvailabilityZone": "us-east-1c",
            "InstanceType": "p2.8xlarge",
            "ProductDescription": "Linux/UNIX",
            "SpotPrice": "2.160000",
            "Timestamp": "2020-03-05T06:09:06.000Z"
        },
        {
            "AvailabilityZone": "us-east-1b",
            "InstanceType": "p2.8xlarge",
            "ProductDescription": "Linux/UNIX",
            "SpotPrice": "2.160000",
            "Timestamp": "2020-03-05T02:46:33.000Z"
        },
        {
            "AvailabilityZone": "us-east-1f",
            "InstanceType": "p2.8xlarge",
            "ProductDescription": "Linux/UNIX",
            "SpotPrice": "7.200000",
            "Timestamp": "2020-03-05T02:46:33.000Z"
        },
        {
            "AvailabilityZone": "us-east-1a",
            "InstanceType": "p2.8xlarge",
            "ProductDescription": "Linux/UNIX",
            "SpotPrice": "2.160000",
            "Timestamp": "2020-03-05T02:46:33.000Z"
        },
        {
            "AvailabilityZone": "us-east-1d",
            "InstanceType": "p2.8xlarge",
            "ProductDescription": "Linux/UNIX",
            "SpotPrice": "2.160000",
            "Timestamp": "2020-03-05T02:46:33.000Z"
        },
        {
            "AvailabilityZone": "us-east-1c",
            "InstanceType": "p2.8xlarge",
            "ProductDescription": "Linux/UNIX",
            "SpotPrice": "2.160000",
            "Timestamp": "2020-03-05T02:46:33.000Z"
        },
        {
            "AvailabilityZone": "us-east-1e",
            "InstanceType": "p2.8xlarge",
            "ProductDescription": "Linux/UNIX",
            "SpotPrice": "2.184900",
            "Timestamp": "2020-03-05T00:47:16.000Z"
        },
        {
            "AvailabilityZone": "us-east-1e",
            "InstanceType": "p2.8xlarge",
            "ProductDescription": "Linux/UNIX",
            "SpotPrice": "2.171600",
            "Timestamp": "2020-03-04T18:30:08.000Z"
        },
        {
            "AvailabilityZone": "us-east-1e",
            "InstanceType": "p2.8xlarge",
            "ProductDescription": "Linux/UNIX",
            "SpotPrice": "2.165500",
            "Timestamp": "2020-03-04T11:56:50.000Z"
        },
        {
            "AvailabilityZone": "us-east-1e",
            "InstanceType": "p2.8xlarge",
            "ProductDescription": "Linux/UNIX",
            "SpotPrice": "2.161300",
            "Timestamp": "2020-03-04T06:55:05.000Z"
        },
        {
            "AvailabilityZone": "us-east-1b",
            "InstanceType": "p2.8xlarge",
            "ProductDescription": "Linux/UNIX",
            "SpotPrice": "2.160000",
            "Timestamp": "2020-03-04T02:45:57.000Z"
        },
        {
            "AvailabilityZone": "us-east-1f",
            "InstanceType": "p2.8xlarge",
            "ProductDescription": "Linux/UNIX",
            "SpotPrice": "7.200000",
            "Timestamp": "2020-03-04T02:45:57.000Z"
        },
        {
            "AvailabilityZone": "us-east-1a",
            "InstanceType": "p2.8xlarge",
            "ProductDescription": "Linux/UNIX",
            "SpotPrice": "2.160000",
            "Timestamp": "2020-03-04T02:45:57.000Z"
        },
        {
            "AvailabilityZone": "us-east-1e",
            "InstanceType": "p2.8xlarge",
            "ProductDescription": "Linux/UNIX",
            "SpotPrice": "2.160000",
            "Timestamp": "2020-03-04T02:45:57.000Z"
        },
        {
            "AvailabilityZone": "us-east-1d",
            "InstanceType": "p2.8xlarge",
            "ProductDescription": "Linux/UNIX",
            "SpotPrice": "2.160000",
            "Timestamp": "2020-03-04T02:45:57.000Z"
        },
        {
            "AvailabilityZone": "us-east-1c",
            "InstanceType": "p2.8xlarge",
            "ProductDescription": "Linux/UNIX",
            "SpotPrice": "2.160000",
            "Timestamp": "2020-03-04T02:45:57.000Z"
        },
        {
            "AvailabilityZone": "us-east-1b",
            "InstanceType": "p2.8xlarge",
            "ProductDescription": "Linux/UNIX",
            "SpotPrice": "2.160000",
            "Timestamp": "2020-03-03T02:45:26.000Z"
        },
        {
            "AvailabilityZone": "us-east-1f",
            "InstanceType": "p2.8xlarge",
            "ProductDescription": "Linux/UNIX",
            "SpotPrice": "7.200000",
            "Timestamp": "2020-03-03T02:45:26.000Z"
        },
        {
            "AvailabilityZone": "us-east-1a",
            "InstanceType": "p2.8xlarge",
            "ProductDescription": "Linux/UNIX",
            "SpotPrice": "2.160000",
            "Timestamp": "2020-03-03T02:45:26.000Z"
        },
        {
            "AvailabilityZone": "us-east-1e",
            "InstanceType": "p2.8xlarge",
            "ProductDescription": "Linux/UNIX",
            "SpotPrice": "2.160000",
            "Timestamp": "2020-03-03T02:45:26.000Z"
        },
        {
            "AvailabilityZone": "us-east-1d",
            "InstanceType": "p2.8xlarge",
            "ProductDescription": "Linux/UNIX",
            "SpotPrice": "2.160000",
            "Timestamp": "2020-03-03T02:45:26.000Z"
        },
        {
            "AvailabilityZone": "us-east-1c",
            "InstanceType": "p2.8xlarge",
            "ProductDescription": "Linux/UNIX",
            "SpotPrice": "2.160000",
            "Timestamp": "2020-03-03T02:45:26.000Z"
        },
        {
            "AvailabilityZone": "us-east-1b",
            "InstanceType": "p2.8xlarge",
            "ProductDescription": "Linux/UNIX",
            "SpotPrice": "2.160000",
            "Timestamp": "2020-03-02T02:44:27.000Z"
        },
        {
            "AvailabilityZone": "us-east-1f",
            "InstanceType": "p2.8xlarge",
            "ProductDescription": "Linux/UNIX",
            "SpotPrice": "7.200000",
            "Timestamp": "2020-03-02T02:44:27.000Z"
        },
        {
            "AvailabilityZone": "us-east-1a",
            "InstanceType": "p2.8xlarge",
            "ProductDescription": "Linux/UNIX",
            "SpotPrice": "2.160000",
            "Timestamp": "2020-03-02T02:44:27.000Z"
        },
        {
            "AvailabilityZone": "us-east-1e",
            "InstanceType": "p2.8xlarge",
            "ProductDescription": "Linux/UNIX",
            "SpotPrice": "2.160000",
            "Timestamp": "2020-03-02T02:44:27.000Z"
        },
        {
            "AvailabilityZone": "us-east-1d",
            "InstanceType": "p2.8xlarge",
            "ProductDescription": "Linux/UNIX",
            "SpotPrice": "2.160000",
            "Timestamp": "2020-03-02T02:44:27.000Z"
        },
        {
            "AvailabilityZone": "us-east-1c",
            "InstanceType": "p2.8xlarge",
            "ProductDescription": "Linux/UNIX",
            "SpotPrice": "2.160000",
            "Timestamp": "2020-03-02T02:44:27.000Z"
        },
        {
            "AvailabilityZone": "us-east-1b",
            "InstanceType": "p2.8xlarge",
            "ProductDescription": "Linux/UNIX",
            "SpotPrice": "2.160000",
            "Timestamp": "2020-03-01T14:44:18.000Z"
        },
        {
            "AvailabilityZone": "us-east-1f",
            "InstanceType": "p2.8xlarge",
            "ProductDescription": "Linux/UNIX",
            "SpotPrice": "7.200000",
            "Timestamp": "2020-03-01T14:44:18.000Z"
        },
        {
            "AvailabilityZone": "us-east-1a",
            "InstanceType": "p2.8xlarge",
            "ProductDescription": "Linux/UNIX",
            "SpotPrice": "2.160000",
            "Timestamp": "2020-03-01T14:44:18.000Z"
        },
        {
            "AvailabilityZone": "us-east-1e",
            "InstanceType": "p2.8xlarge",
            "ProductDescription": "Linux/UNIX",
            "SpotPrice": "2.160000",
            "Timestamp": "2020-03-01T14:44:18.000Z"
        },
        {
            "AvailabilityZone": "us-east-1d",
            "InstanceType": "p2.8xlarge",
            "ProductDescription": "Linux/UNIX",
            "SpotPrice": "2.160000",
            "Timestamp": "2020-03-01T14:44:18.000Z"
        },
        {
            "AvailabilityZone": "us-east-1c",
            "InstanceType": "p2.8xlarge",
            "ProductDescription": "Linux/UNIX",
            "SpotPrice": "2.160000",
            "Timestamp": "2020-03-01T14:44:18.000Z"
        },
        {
            "AvailabilityZone": "us-east-1b",
            "InstanceType": "p2.8xlarge",
            "ProductDescription": "Linux/UNIX",
            "SpotPrice": "2.160000",
            "Timestamp": "2020-02-29T14:43:39.000Z"
        },
        {
            "AvailabilityZone": "us-east-1f",
            "InstanceType": "p2.8xlarge",
            "ProductDescription": "Linux/UNIX",
            "SpotPrice": "7.200000",
            "Timestamp": "2020-02-29T14:43:39.000Z"
        },
        {
            "AvailabilityZone": "us-east-1a",
            "InstanceType": "p2.8xlarge",
            "ProductDescription": "Linux/UNIX",
            "SpotPrice": "2.160000",
            "Timestamp": "2020-02-29T14:43:39.000Z"
        },
        {
            "AvailabilityZone": "us-east-1e",
            "InstanceType": "p2.8xlarge",
            "ProductDescription": "Linux/UNIX",
            "SpotPrice": "2.160000",
            "Timestamp": "2020-02-29T14:43:39.000Z"
        },
        {
            "AvailabilityZone": "us-east-1d",
            "InstanceType": "p2.8xlarge",
            "ProductDescription": "Linux/UNIX",
            "SpotPrice": "2.160000",
            "Timestamp": "2020-02-29T14:43:39.000Z"
        },
        {
            "AvailabilityZone": "us-east-1c",
            "InstanceType": "p2.8xlarge",
            "ProductDescription": "Linux/UNIX",
            "SpotPrice": "2.160000",
            "Timestamp": "2020-02-29T14:43:39.000Z"
        },
        {
            "AvailabilityZone": "us-east-1b",
            "InstanceType": "p2.8xlarge",
            "ProductDescription": "Linux/UNIX",
            "SpotPrice": "2.160000",
            "Timestamp": "2020-02-29T01:44:50.000Z"
        },
        {
            "AvailabilityZone": "us-east-1f",
            "InstanceType": "p2.8xlarge",
            "ProductDescription": "Linux/UNIX",
            "SpotPrice": "7.200000",
            "Timestamp": "2020-02-29T01:44:50.000Z"
        },
        {
            "AvailabilityZone": "us-east-1a",
            "InstanceType": "p2.8xlarge",
            "ProductDescription": "Linux/UNIX",
            "SpotPrice": "2.160000",
            "Timestamp": "2020-02-29T01:44:50.000Z"
        },
        {
            "AvailabilityZone": "us-east-1e",
            "InstanceType": "p2.8xlarge",
            "ProductDescription": "Linux/UNIX",
            "SpotPrice": "2.160000",
            "Timestamp": "2020-02-29T01:44:50.000Z"
        },
        {
            "AvailabilityZone": "us-east-1d",
            "InstanceType": "p2.8xlarge",
            "ProductDescription": "Linux/UNIX",
            "SpotPrice": "2.160000",
            "Timestamp": "2020-02-29T01:44:50.000Z"
        },
        {
            "AvailabilityZone": "us-east-1c",
            "InstanceType": "p2.8xlarge",
            "ProductDescription": "Linux/UNIX",
            "SpotPrice": "2.160000",
            "Timestamp": "2020-02-29T01:44:50.000Z"
        },
        {
            "AvailabilityZone": "us-east-1b",
            "InstanceType": "p2.8xlarge",
            "ProductDescription": "Linux/UNIX",
            "SpotPrice": "2.160000",
            "Timestamp": "2020-02-28T01:44:24.000Z"
        },
        {
            "AvailabilityZone": "us-east-1f",
            "InstanceType": "p2.8xlarge",
            "ProductDescription": "Linux/UNIX",
            "SpotPrice": "7.200000",
            "Timestamp": "2020-02-28T01:44:24.000Z"
        },
        {
            "AvailabilityZone": "us-east-1a",
            "InstanceType": "p2.8xlarge",
            "ProductDescription": "Linux/UNIX",
            "SpotPrice": "2.160000",
            "Timestamp": "2020-02-28T01:44:24.000Z"
        },
        {
            "AvailabilityZone": "us-east-1e",
            "InstanceType": "p2.8xlarge",
            "ProductDescription": "Linux/UNIX",
            "SpotPrice": "2.160000",
            "Timestamp": "2020-02-28T01:44:24.000Z"
        },
        {
            "AvailabilityZone": "us-east-1d",
            "InstanceType": "p2.8xlarge",
            "ProductDescription": "Linux/UNIX",
            "SpotPrice": "2.160000",
            "Timestamp": "2020-02-28T01:44:24.000Z"
        },
        {
            "AvailabilityZone": "us-east-1c",
            "InstanceType": "p2.8xlarge",
            "ProductDescription": "Linux/UNIX",
            "SpotPrice": "2.160000",
            "Timestamp": "2020-02-28T01:44:24.000Z"
        },
        {
            "AvailabilityZone": "us-east-1b",
            "InstanceType": "p2.8xlarge",
            "ProductDescription": "Linux/UNIX",
            "SpotPrice": "2.160000",
            "Timestamp": "2020-02-27T13:44:29.000Z"
        },
        {
            "AvailabilityZone": "us-east-1f",
            "InstanceType": "p2.8xlarge",
            "ProductDescription": "Linux/UNIX",
            "SpotPrice": "7.200000",
            "Timestamp": "2020-02-27T13:44:29.000Z"
        },
        {
            "AvailabilityZone": "us-east-1a",
            "InstanceType": "p2.8xlarge",
            "ProductDescription": "Linux/UNIX",
            "SpotPrice": "2.160000",
            "Timestamp": "2020-02-27T13:44:29.000Z"
        },
        {
            "AvailabilityZone": "us-east-1e",
            "InstanceType": "p2.8xlarge",
            "ProductDescription": "Linux/UNIX",
            "SpotPrice": "2.160000",
            "Timestamp": "2020-02-27T13:44:29.000Z"
        },
        {
            "AvailabilityZone": "us-east-1d",
            "InstanceType": "p2.8xlarge",
            "ProductDescription": "Linux/UNIX",
            "SpotPrice": "2.160000",
            "Timestamp": "2020-02-27T13:44:29.000Z"
        },
        {
            "AvailabilityZone": "us-east-1c",
            "InstanceType": "p2.8xlarge",
            "ProductDescription": "Linux/UNIX",
            "SpotPrice": "2.160000",
            "Timestamp": "2020-02-27T13:44:29.000Z"
        },
        {
            "AvailabilityZone": "us-east-1b",
            "InstanceType": "p2.8xlarge",
            "ProductDescription": "Linux/UNIX",
            "SpotPrice": "2.160000",
            "Timestamp": "2020-02-26T13:43:38.000Z"
        },
        {
            "AvailabilityZone": "us-east-1f",
            "InstanceType": "p2.8xlarge",
            "ProductDescription": "Linux/UNIX",
            "SpotPrice": "7.200000",
            "Timestamp": "2020-02-26T13:43:38.000Z"
        },
        {
            "AvailabilityZone": "us-east-1a",
            "InstanceType": "p2.8xlarge",
            "ProductDescription": "Linux/UNIX",
            "SpotPrice": "2.160000",
            "Timestamp": "2020-02-26T13:43:38.000Z"
        },
        {
            "AvailabilityZone": "us-east-1e",
            "InstanceType": "p2.8xlarge",
            "ProductDescription": "Linux/UNIX",
            "SpotPrice": "2.160000",
            "Timestamp": "2020-02-26T13:43:38.000Z"
        },
        {
            "AvailabilityZone": "us-east-1d",
            "InstanceType": "p2.8xlarge",
            "ProductDescription": "Linux/UNIX",
            "SpotPrice": "2.160000",
            "Timestamp": "2020-02-26T13:43:38.000Z"
        },
        {
            "AvailabilityZone": "us-east-1c",
            "InstanceType": "p2.8xlarge",
            "ProductDescription": "Linux/UNIX",
            "SpotPrice": "2.160000",
            "Timestamp": "2020-02-26T13:43:38.000Z"
        }
    ]
}
